neurodent/__init__.py
neurodent/constants.py
neurodent/core/__init__.py
neurodent/core/analysis.py
neurodent/core/analyze_frag.py
neurodent/core/analyze_sort.py
neurodent/core/core.py
neurodent/core/frequency_domain_spike_detection.py
neurodent/core/utils.py
neurodent/visualization/__init__.py
neurodent/visualization/frequency_domain_results.py
neurodent/visualization/results.py
neurodent/visualization/plotting/__init__.py
neurodent/visualization/plotting/animal.py
neurodent/visualization/plotting/experiment.py
neurodent-0.2.4.dist-info/licenses/LICENSE
neurodent-0.2.4.dist-info/METADATA
neurodent-0.2.4.dist-info/WHEEL
neurodent-0.2.4.dist-info/top_level.txt
neurodent-0.2.4.dist-info/RECORD
