Metadata-Version: 2.4
Name: neurodent
Version: 0.2.4
Summary: Rodent EEG analysis tools
Author-email: Joseph Dong <dongjp@chop.edu>, Yongtaek Oh <ohy2@chop.edu>, Eric Marsh <marshe@chop.edu>
License-Expression: MIT
Project-URL: Homepage, https://github.com/josephdong1000/neurodent
Project-URL: Documentation, https://josephdong1000.github.io/neurodent/
Project-URL: Repository, https://github.com/josephdong1000/neurodent
Project-URL: Issue Tracker, https://github.com/josephdong1000/neurodent/issues
Keywords: EEG,rodent,neuroscience,data analysis,pipeline,PythonEEG,PyEEG
Classifier: Development Status :: 4 - Beta
Classifier: Intended Audience :: Science/Research
Classifier: Programming Language :: Python :: 3
Classifier: Programming Language :: Python :: 3.10
Classifier: Programming Language :: Python :: 3.11
Classifier: Programming Language :: Python :: 3.12
Classifier: Programming Language :: Python :: 3.13
Classifier: Topic :: Scientific/Engineering :: Medical Science Apps.
Classifier: Operating System :: OS Independent
Requires-Python: >=3.10
License-File: LICENSE
Requires-Dist: numpy
Requires-Dist: matplotlib
Requires-Dist: mne
Requires-Dist: mne-connectivity
Requires-Dist: pandas
Requires-Dist: spikeinterface
Requires-Dist: probeinterface
Requires-Dist: scipy
Requires-Dist: dask[distributed]
Requires-Dist: dask-jobqueue
Requires-Dist: seaborn
Requires-Dist: pyarrow
Requires-Dist: statannotations
Requires-Dist: statsmodels
Requires-Dist: django
Requires-Dist: openpyxl
Requires-Dist: appnope
Requires-Dist: zarr>=2.18.3
Requires-Dist: scikit-learn>=1.7.2
Provides-Extra: pipeline
Requires-Dist: snakemake>=7.32.4; extra == "pipeline"
Requires-Dist: pulp==2.7.0; python_full_version < "3.11" and extra == "pipeline"
Provides-Extra: all
Requires-Dist: snakemake>=7.32.4; extra == "all"
Requires-Dist: pulp==2.7.0; python_full_version < "3.11" and extra == "all"
Dynamic: license-file
